events/__init__.py
events/_collections.py
events/_common.py
events/_field.py
events/_property.py
events/_utils.py
cs_events-0.5.0.dist-info/LICENSE
cs_events-0.5.0.dist-info/METADATA
cs_events-0.5.0.dist-info/WHEEL
cs_events-0.5.0.dist-info/RECORD
