Metadata-Version: 2.1
Name: cs-events
Version: 0.5.0
Summary: C#-style event handling mechanism for Python
Home-page: https://github.com/wise0704/python-cs-events
License: MIT
Keywords: python,event,c#
Author: Daniel Jeong
Author-email: wise0704@outlook.com
Requires-Python: >=3.10,<4.0
Classifier: Development Status :: 4 - Beta
Classifier: Intended Audience :: Developers
Classifier: License :: OSI Approved :: MIT License
Classifier: Natural Language :: English
Classifier: Operating System :: OS Independent
Classifier: Programming Language :: Python :: 3
Classifier: Programming Language :: Python :: 3.10
Classifier: Programming Language :: Python :: 3.11
Classifier: Programming Language :: Python :: 3.12
Classifier: Topic :: Software Development :: Libraries
Classifier: Typing :: Typed
Requires-Dist: typing-extensions (>=4.0.1,<5.0.0) ; python_version < "3.12"
Project-URL: Issues, https://github.com/wise0704/python-cs-events/issues
Project-URL: Repository, https://github.com/wise0704/python-cs-events
